{
  "866772444127690832": [
    {
      "id": 869925207295553577,
      "name": "PvE",
      "reaction_emoji": "\u270c\ufe0f",
      "is_custom_emoji": false
    },
    {
      "id": 869925143605035118,
      "name": "PvP",
      "reaction_emoji": "<:PvP:867410944988807198>",
      "is_custom_emoji": true
    },
    {
      "id": 869925363550138368,
      "name": "DPS",
      "reaction_emoji": "\ud83d\udde1\ufe0f",
      "is_custom_emoji": false
    },
    {
      "id": 869925301449281578,
      "name": "Healer",
      "reaction_emoji": "<:Heal:867410945076232192>",
      "is_custom_emoji": true
    },
    {
      "id": 869925260621922344,
      "name": "Tank",
      "reaction_emoji": "\ud83d\udee1\ufe0f",
      "is_custom_emoji": false
    },
    {
      "id": 869924163454894100,
      "name": "Gathering",
      "reaction_emoji": "<:gather:869931224632807424>",
      "is_custom_emoji": true
    },
    {
      "id": 869924390928781352,
      "name": "Omnicrafter",
      "reaction_emoji": "<:omi:869931745812807751>",
      "is_custom_emoji": true
    },
    {
      "id": 869924113999880223,
      "name": "Furnishing",
      "reaction_emoji": "<:furn:869931223936557117>",
      "is_custom_emoji": true
    },
    {
      "id": 869924049105600533,
      "name": "Cooking",
      "reaction_emoji": "<:Cook:869931224175612004>",
      "is_custom_emoji": true
    },
    {
      "id": 869923776521990145,
      "name": "Arcana",
      "reaction_emoji": "<:Arcana:869951022037090414>",
      "is_custom_emoji": true
    },
    {
      "id": 869923715750694963,
      "name": "Jewelcrafting",
      "reaction_emoji": "<:jewel:869931224217571328>",
      "is_custom_emoji": true
    },
    {
      "id": 869923650097278996,
      "name": "Engineering",
      "reaction_emoji": "<:eng:869931223806525531>",
      "is_custom_emoji": true
    },
    {
      "id": 869922995265765456,
      "name": "Armoring",
      "reaction_emoji": "<:arm:869929856090144840>",
      "is_custom_emoji": true
    },
    {
      "id": 869922812310196244,
      "name": "Weaponsmithing",
      "reaction_emoji": "<:wep:869929871789400144>",
      "is_custom_emoji": true
    }
  ]
}